odoo8_addon_account_invoice_zugferd-8.0.1.0.0.99.dev13-nspkg.pth
odoo_addons/account_invoice_zugferd/README.rst
odoo_addons/account_invoice_zugferd/__init__.py
odoo_addons/account_invoice_zugferd/__openerp__.py
odoo_addons/account_invoice_zugferd/data/ZUGFeRD1p0.xsd
odoo_addons/account_invoice_zugferd/data/ZUGFeRD1p0_urn_un_unece_uncefact_data_standard_QualifiedDataType_12.xsd
odoo_addons/account_invoice_zugferd/data/ZUGFeRD1p0_urn_un_unece_uncefact_data_standard_ReusableAggregateBusinessInformationEntity_12.xsd
odoo_addons/account_invoice_zugferd/data/ZUGFeRD1p0_urn_un_unece_uncefact_data_standard_UnqualifiedDataType_15.xsd
odoo_addons/account_invoice_zugferd/data/ZUGFeRD_extension_schema.xmp
odoo_addons/account_invoice_zugferd/i18n/account_invoice_zugferd.pot
odoo_addons/account_invoice_zugferd/i18n/fr.po
odoo_addons/account_invoice_zugferd/i18n/pt_BR.po
odoo_addons/account_invoice_zugferd/models/__init__.py
odoo_addons/account_invoice_zugferd/models/account_invoice.py
odoo_addons/account_invoice_zugferd/models/report.py
odoo_addons/account_invoice_zugferd/static/description/icon.png
odoo_addons/account_invoice_zugferd/tests/__init__.py
odoo_addons/account_invoice_zugferd/tests/test_zugferd_invoice.py
odoo8_addon_account_invoice_zugferd-8.0.1.0.0.99.dev13.dist-info/METADATA
odoo8_addon_account_invoice_zugferd-8.0.1.0.0.99.dev13.dist-info/WHEEL
odoo8_addon_account_invoice_zugferd-8.0.1.0.0.99.dev13.dist-info/namespace_packages.txt
odoo8_addon_account_invoice_zugferd-8.0.1.0.0.99.dev13.dist-info/top_level.txt
odoo8_addon_account_invoice_zugferd-8.0.1.0.0.99.dev13.dist-info/RECORD
